faery/__init__.py
faery/__main__.py
faery/color.py
faery/display.py
faery/enums.py
faery/event_camera_input.py
faery/event_rate.py
faery/events_filter.py
faery/events_input.py
faery/events_render.py
faery/events_stream.py
faery/events_stream_state.py
faery/extension.cpython-311-x86_64-linux-gnu.so
faery/file_decoder.py
faery/file_encoder.py
faery/frame_filter.py
faery/frame_input.py
faery/frame_stream.py
faery/frame_stream_state.py
faery/kinectograph.py
faery/spectrogram.py
faery/stream.py
faery/svg.py
faery/task.py
faery/timestamp.py
faery/udp_decoder.py
faery/udp_encoder.py
faery/wiggle.py
faery/cli/__init__.py
faery/cli/colormaps.py
faery/cli/command.py
faery/cli/coolname.py
faery/cli/faery_script.mustache
faery/cli/info.py
faery/cli/init.py
faery/cli/list_filters.py
faery/cli/process.py
faery/cli/run.py
faery/colormaps/__init__.py
faery/colormaps/_base.py
faery/colormaps/acton.py
faery/colormaps/bam.py
faery/colormaps/bam_o.py
faery/colormaps/bamako.py
faery/colormaps/batlow.py
faery/colormaps/batlow_k.py
faery/colormaps/batlow_w.py
faery/colormaps/berlin.py
faery/colormaps/bilbao.py
faery/colormaps/broc.py
faery/colormaps/broc_o.py
faery/colormaps/buda.py
faery/colormaps/cork.py
faery/colormaps/cork_o.py
faery/colormaps/davos.py
faery/colormaps/devon.py
faery/colormaps/glasgow.py
faery/colormaps/gray.py
faery/colormaps/hawaii.py
faery/colormaps/imola.py
faery/colormaps/lajolla.py
faery/colormaps/lapaz.py
faery/colormaps/lipari.py
faery/colormaps/lisbon.py
faery/colormaps/managua.py
faery/colormaps/navia.py
faery/colormaps/navia_white.py
faery/colormaps/nuuk.py
faery/colormaps/oslo.py
faery/colormaps/roma.py
faery/colormaps/roma_o.py
faery/colormaps/starry_night.py
faery/colormaps/tofino.py
faery/colormaps/tokyo.py
faery/colormaps/turku.py
faery/colormaps/vanimo.py
faery/colormaps/vik.py
faery/colormaps/vik_o.py
faery/types/aedat.pyi
faery/types/csv.pyi
faery/types/dat.pyi
faery-0.7.0.dist-info/METADATA
faery-0.7.0.dist-info/WHEEL
faery-0.7.0.dist-info/entry_points.txt
faery-0.7.0.dist-info/RECORD
faery-0.7.0.dist-info/licenses/LICENSE
