Metadata-Version: 2.4
Name: faery
Version: 0.7.0
Requires-Dist: numpy>=1.26
Requires-Dist: pytest==8.3.3 ; extra == 'tests'
Provides-Extra: tests
License-File: LICENSE
Summary: Ferries event-based data from A to B
Author-email: Alexandre Marcireau <alexandre.marcireau@gmail.com>, Jens Egholm Pedersen <jens@jepedersen.dk>, Gregor Lenz <gregor@neurobus.space>
Requires-Python: >=3.9
Project-URL: homepage, https://github.com/aestream/faery/
Project-URL: repository, https://github.com/aestream/faery/
Project-URL: documentation, https://github.com/aestream/faery/
